<_templates Include="trucks" />
<TruckAddon>
	<TruckData>
		<Damage>
			<Multiplier Multiplier="1.0" Type="Engine" />
		</Damage>
	</TruckData>
	<PhysicsModel Mesh="trucks/navistar_5000mv_tuning/navistar_5000mv_bumper_02">
		<Body Mass="100">
			<Constraint Type="Rigid" />
		</Body>
	</PhysicsModel>
	<GameData
		CameraPreset="hoods"
		Category="bumper"
		Price="2500"
		UnlockByExploration="false"
		UnlockByRank="13"
	>
		<UiDesc
			UiDesc="UI_TUNING_BUMPER_HEAVYDUTY_DESC"
			UiIcon30x30=""
			UiIcon40x40=""
			UiName="UI_TUNING_BUMPER_HEAVYDUTY_NAME"
		/>
		<InstallSocket Type="Navistar5000mvBumper" />
	</GameData>
</TruckAddon>
