<_templates Include="trucks" />
<TruckAddon>
	<PhysicsModel Mesh="trucks/paystar_5600ts_tuning/paystar_5600ts_gabarite_2" />
	<ModelAttachments>
		<Ignition>
			<Flare _template="MarkerBeacon" Pos="(4.189; 2.956; -0.804)" />
			<Flare _template="MarkerBeacon" Pos="(4.189; 2.956; 0.804)" />
		</Ignition>
	</ModelAttachments>
	<GameData
		CameraPreset="roof"
		Category="miscellenious"
		Price="800"
		UnlockByExploration="false"
		UnlockByRank="1"
	>
		<UiDesc
			UiDesc="UI_TUNING_PARKINGLIGHTS_TRI_TWO_DESC"
			UiIcon30x30=""
			UiIcon40x40=""
			UiName="UI_TUNING_PARKINGLIGHTS_TRI_TWO_NAME"
		/>
		<InstallSocket Type="paystar5600TsGabarite2" />
	</GameData>
</TruckAddon>
